{
  "team": [
    { "id":"1",
      "name": {
        "ar": "باتل بن عبد الله بن حمدان الباتل",
        "en": "Batel bin Abdullah bin Hamdan Al-Batel"
      },
      "job_title": {
        "ar": "رئيس فريق العمل الشريك المؤسس",
        "en": "Team Leader and Co-Founder"
      },
      "nationality": {
        "ar": "سعودي",
        "en": "Saudi"
      },
      "field": {
        "ar": "مستشار ومحاسب قانوني معتمد",
        "en": "Certified Legal Accountant and Consultant"
      },
      "degree": {
        "ar": "الماجستير في المحاسبة من جامعة ميامي الأمريكية",
        "en": "Master's in Accounting from the University of Miami, USA"
      },
      "experience_years": {
        "ar": "أكثر من 20 سنة",
        "en": "More than 20 years"
      },
      "qualifications": [
        {
          "title": {
            "ar": "زمالة المحاسبين القانونيين السعودية",
            "en": "Saudi Organization for Certified Public Accountants (SOCPA)"
          },
          "abbreviation": {
            "ar": "SOCPA",
            "en": "SOCPA"
          }
        },
        {
          "title": {
            "ar": "زمالة المستشار المالي الأمريكي",
            "en": "Certified Financial Consultant (CFC)"
          },
          "abbreviation": {
            "ar": "CFC",
            "en": "CFC"
          }
        },
        {
          "title": {
            "ar": "شهادة مدير الأعمال المعتمد الكندية",
            "en": "Certified Business Administrator (CBA)"
          },
          "abbreviation": {
            "ar": "CBA",
            "en": "CBA"
          }
        },
        {
          "title": {
            "ar": "شهادة الماجستير في المحاسبة من جامعة ميامي الأمريكية",
            "en": "Master's in Accounting from the University of Miami, USA"
          }
        },
        {
          "title": {
            "ar": "شهادة البكالوريوس في المحاسبة من جامعة الإمام محمد بن سعود الإسلامية بتقدير ممتاز",
            "en": "Bachelor's in Accounting from Imam Muhammad Ibn Saud Islamic University with Excellent Distinction"
          }
        },
        {
          "title": {
            "ar": "العديد من الدورات التدريبية داخل وخارج المملكة العربية السعودية، ومن خلالها اكتسب خبرات عملية عديدة من عمله كمدير ومستشار مالي في مجموعة شركات خاصة، وهو حاصل على ترخيص مزاولة مهنة المحاسبة القانونية والاستشارات المالية.",
            "en": "Completed numerous training courses inside and outside Saudi Arabia, gaining extensive practical experience as a financial manager and consultant in private companies. He is licensed to practice legal accounting and financial consulting."
          }
        }
      ],
     
      "image": {
        "url": "https://media.licdn.com/dms/image/v2/D4D0BAQHhTiXcUzqYeA/company-logo_200_200/company-logo_200_200/0/1711368279830/albatel_cpa_logo?e=2147483647&v=beta&t=CgruAhN_mJz9RYhR9nWO3bZJ0NEwfEQ_vQVbocOjEf4",
        "description": {
          "ar": "صورة للسيرة الذاتية لباتل بن عبد الله بن حمدان الباتل",
          "en": "Resume image of Batel bin Abdullah bin Hamdan Al-Batel"
        }
      }
    },
    { "id":"2",
      "name": {
        "ar": "أيمن فؤاد محمود سراج الدين",
        "en": "Ayman Fouad Mahmoud Sirajuddin"
      },
      "job_title": {
        "ar": "مستشار مالي ومراجع معتمد",
        "en": "Certified Financial Consultant and Auditor"
      },
      "nationality": {
        "ar": "مصري",
        "en": "Egyptian"
      },
      "field": {
        "ar": "المحاسبة والمراجعة الداخلية والتدقيق الخارجي",
        "en": "Accounting, Internal and External Auditing"
      },
      "degree": {
        "ar": "بكالوريوس محاسبة",
        "en": "Bachelor's in Accounting"
      },
      "experience_years": {
        "ar": "أكثر من 25 سنة",
        "en": "More than 25 years"
      },
      "qualifications": [
        {
          "title": {
            "ar": "زمالة المدقق الداخلي المعتمد من المعهد الدولي للمدققين الداخليين",
            "en": "Certified Internal Auditor (CIA) from the Institute of Internal Auditors"
          },
          "abbreviation": {
            "ar": "CIA",
            "en": "CIA"
          }
        },
        {
          "title": {
            "ar": "زمالة الهيئة السعودية للمحاسبين القانونيين",
            "en": "Certified Public Accountant from the Saudi Organization for Certified Public Accountants (SOCPA)"
          },
          "abbreviation": {
            "ar": "SOCPA",
            "en": "SOCPA"
          }
        },
        {
          "title": {
            "ar": "زمالة المراقب والمدقق الشرعي من هيئة المحاسبة والمراجعة للبنوك والمؤسسات المالية الإسلامية",
            "en": "Certified Sharia Auditor and Advisor (CSAA) from the Accounting and Auditing Organization for Islamic Financial Institutions"
          },
          "abbreviation": {
            "ar": "CSAA",
            "en": "CSAA"
          }
        },
        {
          "title": {
            "ar": "زمالة المحاسب القانوني الإسلامي من هيئة المحاسبة والمراجعة للبنوك والمؤسسات المالية الإسلامية",
            "en": "Certified Islamic Professional Accountant (CIPA) from the Accounting and Auditing Organization for Islamic Financial Institutions"
          },
          "abbreviation": {
            "ar": "CIPA",
            "en": "CIPA"
          }
        },
        {
          "title": {
            "ar": "زمالة المصرف الإسلامي المعتمد من المجلس العام للبنوك والمؤسسات المالية الإسلامية",
            "en": "Certified Islamic Banker (CIB) from the General Council for Islamic Banks and Financial Institutions"
          },
          "abbreviation": {
            "ar": "CIB",
            "en": "CIB"
          }
        },
        {
          "title": {
            "ar": "بكالوريوس تجارة تخصص محاسبة جامعة الإسكندرية سنة 1987 م، تقدير عام جيد جدا",
            "en": "Bachelor of Commerce, Accounting, Alexandria University, 1987, Very Good overall rating"
          }
        },
        {
          "title": {
            "ar": "والعديد من الدورات التدريبية داخل وخارج المملكة العربية السعودية.",
            "en": "Attended numerous training courses inside and outside Saudi Arabia."
          }
        }
      ],
      
      "image": {
        "url": "https://media.licdn.com/dms/image/v2/D4D0BAQHhTiXcUzqYeA/company-logo_200_200/company-logo_200_200/0/1711368279830/albatel_cpa_logo?e=2147483647&v=beta&t=CgruAhN_mJz9RYhR9nWO3bZJ0NEwfEQ_vQVbocOjEf4",
        "description": {
          "ar": "صورة للسيرة الذاتية لأيمن فؤاد محمود سراج الدين",
          "en": "Resume image of Ayman Fouad Mahmoud Sirajuddin"
        }
      }
    },
    { "id":"3",
      "name": {
        "ar": "ياسر أحمد السبعي",
        "en": "Yasser Ahmed Al-Sebaie"
      },
      "job_title": {
        "ar": "استشاري الرقابة والجودة وإدارة المخاطر واستمرارية الأعمال والالتزام",
        "en": "Consultant in Control, Quality, Risk Management, Business Continuity, and Compliance"
      },
      "nationality": {
        "ar": "مصري",
        "en": "Egyptian"
      },
      "field": {
        "ar": "المحاسبة والمراجعة الداخلية والتدقيق الخارجي",
        "en": "Accounting, Internal and External Auditing"
      },
      "degree": {
        "ar": "بكالوريوس محاسبة",
        "en": "Bachelor's in Accounting"
      },
      "experience_years": {
        "ar": "تزيد عن 15 عام",
        "en": "More than 15 years"
      },
      "qualifications": [
        {
          "title": {
            "ar": "زمالة الهيئة السعودية للمحاسبين القانونيين",
            "en": "Certified Public Accountant from the Saudi Organization for Certified Public Accountants (SOCPA)"
          },
          "abbreviation": {
            "ar": "SOCPA",
            "en": "SOCPA"
          }
        },
        {
          "title": {
            "ar": "شهادة معايير المحاسبة الدولية من الهيئة المتعاقد معها البريطاني",
            "en": "Certified IFRS from the International Accounting Standards Board (IASB)"
          },
          "abbreviation": {
            "ar": "CERTIFRS",
            "en": "CERTIFRS"
          }
        },
        {
          "title": {
            "ar": "زمالة المراقب والمدقق الشرعي من هيئة المحاسبة والمراجعة للبنوك والمؤسسات المالية الإسلامية",
            "en": "Certified Sharia Auditor and Advisor (CSAA) from the Accounting and Auditing Organization for Islamic Financial Institutions"
          },
          "abbreviation": {
            "ar": "CSAA",
            "en": "CSAA"
          }
        },
        {
          "title": {
            "ar": "زمالة المحاسب القانوني الإسلامي من هيئة المحاسبة والمراجعة للبنوك والمؤسسات المالية الإسلامية",
            "en": "Certified Islamic Professional Accountant (CIPA) from the Accounting and Auditing Organization for Islamic Financial Institutions"
          },
          "abbreviation": {
            "ar": "CIPA",
            "en": "CIPA"
          }
        },
        {
          "title": {
            "ar": "ماجستير التمويل الإسلامي المعتمد",
            "en": "Master of Business Administration (MBA) in Islamic Finance"
          },
          "abbreviation": {
            "ar": "MBA",
            "en": "MBA"
          }
        },
        {
          "title": {
            "ar": "فاحص احتيال أمريكي معتمد",
            "en": "Certified Fraud Examiner (CFE)"
          },
          "abbreviation": {
            "ar": "CFE",
            "en": "CFE"
          }
        },
        {
          "title": {
            "ar": "مدقق نظم معلومات أمريكي معتمد",
            "en": "Certified Information Systems Auditor (CISA)"
          },
          "abbreviation": {
            "ar": "CISA",
            "en": "CISA"
          }
        },
        {
          "title": {
            "ar": "مدير مالي معتمد",
            "en": "Certified Financial Manager (CFM)"
          },
          "abbreviation": {
            "ar": "CFM",
            "en": "CFM"
          }
        },
        
        {
          "title": {
            "ar": "شهادة أخصائي الرقابة الداخلية الأمريكية المعتمد",
            "en": "Certified Internal Control Auditor (CICA)"
          },
          "abbreviation": {
            "ar": "CICA",
            "en": "CICA"
          }
        },
        {
          "title": {
            "ar": "العديد من الدورات التدريبية داخل وخارج المملكة العربية السعودية.",
            "en": "Attended numerous training courses inside and outside Saudi Arabia."
          }
        }

      ],
     
      "image": {
        "url": "https://media.licdn.com/dms/image/v2/D4D03AQFBqv67mwv0dQ/profile-displayphoto-shrink_800_800/profile-displayphoto-shrink_800_800/0/1715604744613?e=1731542400&v=beta&t=o-IM1e2RCgXEsOrUH6a46JmWW-ohhDLiGSg_vPav3GY",
        "description": {
          "ar": "صورة للسيرة الذاتية لياسر أحمد السبعي",
          "en": "Resume image of Yasser Ahmed Al-Sebaie"
        }
      }
    },
    { "id":"4",
    "name": {
      "ar": "صبحي محمد جابر",
      "en": "Sobhi Mohammed Jaber"
    },
    "job_title": {
      "ar": "محاسب ومراجع مالي",
        "en": "Accountant and Financial Auditor"
    },
    "nationality": {
      "ar": "مصري",
        "en": "Egyptian"
    },
    "field": {
      "ar": "المحاسبة والمراجعة الداخلية والتدقيق الخارجي",
      "en": "Accounting, Internal and External Auditing"
    },
    "degree": {
      "ar": "بكالوريوس محاسبة",
      "en": "Bachelor's in Accounting"
    },
    "experience_years": {
      "ar": "تزيد عن 15 عام",
      "en": "More than 15 years"
    },
    "qualifications": [
      {
        "title": {
          "ar": "شهادة المراجع الداخلي المعتمد",
          "en": "Certified Internal Auditor Certificate(CIA)"
        },
        "abbreviation": {
          "ar": "CIA",
          "en": "CIA"
        }
      },
      {
        "title": {
          "ar": "شهادة معايير المحاسبة الدولية من الهيئة المتعاقد معها البريطاني",
          "en": "Certified IFRS from the International Accounting Standards Board "
        },
        "abbreviation": {
          "ar": "CERTIFRS",
          "en": "CERTIFRS"
        }
      },
      
      {
        "title": {
          "ar": "زمالة المحاسب القانوني الإسلامي من هيئة المحاسبة والمراجعة للبنوك والمؤسسات المالية الإسلامية",
          "en": "Certified Islamic Professional Accountant (CIPA) from the Accounting and Auditing Organization for Islamic Financial Institutions"
        },
        "abbreviation": {
          "ar": "CIPA",
          "en": "CIPA"
        }
      },
    
      {
        "title": {
          "ar": "بكالوريوس تجارة تخصص محاسبة جامعة الإسكندرية تقدير عام جيد جدا  ",
          "en": "Bachelor of Commerce, Accounting, Alexandria University, Very Good Overall Rating"
        }
      }
      ,
    
      {
        "title": {
          "ar": "العديد من الدورات التدريبية داخل وخارج المملكة العربية السعودية.",
          "en": "Attended numerous training courses inside and outside Saudi Arabia."
        }
      }
    ],
   
    "image": {
      "url": "https://media.licdn.com/dms/image/v2/D4D0BAQHhTiXcUzqYeA/company-logo_200_200/company-logo_200_200/0/1711368279830/albatel_cpa_logo?e=2147483647&v=beta&t=CgruAhN_mJz9RYhR9nWO3bZJ0NEwfEQ_vQVbocOjEf4",
      "description": {
        "ar": "صورة للسيرة الذاتية لصبحي محمد جابر",
          "en": "Resume image of Sobhy Mohamed Gaber"
      }
    }
  },
  { "id":"5",
  "name": {
    "ar": "أسامة هاشم",
    "en": "Osama Hashem"
  },
  "job_title": {
    "ar": "محاسب ومراجع مالي",
      "en": "Accountant and Financial Auditor"
  },
  "nationality": {
    "ar": "مصري",
      "en": "Egyptian"
  },
  "field": {
    "ar": "المحاسبة والتدقيق الخارجي",
    "en": "Accounting and External Auditing"
  },
  "degree": {
    "ar": "بكالوريوس محاسبة",
    "en": "Bachelor's in Accounting"
  },
  "experience_years": {
    "ar": "تزيد عن 12 عام",
    "en": "More than 12 years"
  },
  "qualifications": [
    {
      "title": {
        "ar": "زمالة المعهد الأمريكي للمحاسبين القانونيين من ولاية ميتشاجن",
        "en": "Certified Public Accountant (CPA) from the American Institute of Certified Public Accountants (AICPA) in Michigan"
      },
      "abbreviation": {
        "ar": "CPA",
        "en": "CPA"
      }
    },
    {
      "title": {
        "ar": "عضو جمعية المحاسبين والمراجعين المصرية",
        "en": "Member of the Egyptian Society of Accountants and Auditors"
      },
      "abbreviation": {
        "ar": "ESAA",
        "en": "ESAA"
      }
    },
    {
      "title": {
        "ar": "دبلوم الدراسات العليا في مراجعة الحسابات – جامعة عين شمس",
        "en": "Postgraduate Diploma in Auditing – Ain Shams University"
      }
    },
    {
      "title": {
        "ar": "بكالوريوس تجارة شعبة محاسبة – جامعة بني سويف",
        "en": "Bachelor's Degree in Commerce, majoring in Accounting – Beni-Suef University"
      }
    }
    ,
  
    {
      "title": {
        "ar": "العديد من الدورات التدريبية داخل وخارج المملكة العربية السعودية.",
        "en": "Attended numerous training courses inside and outside Saudi Arabia."
      }
    }
  ],
 
  "image": {
    "url": "https://media.licdn.com/dms/image/v2/D4D0BAQHhTiXcUzqYeA/company-logo_200_200/company-logo_200_200/0/1711368279830/albatel_cpa_logo?e=2147483647&v=beta&t=CgruAhN_mJz9RYhR9nWO3bZJ0NEwfEQ_vQVbocOjEf4",
    "description": {
      "ar": "صورة للسيرة الذاتية لأسامة هاشم",
      "en": "Resume image of Osama Hashem"
    }
  }
},
{ "id":"5",
"name": {
  "ar": "مصطفى عبد الله عبيد",
  "en": "Mostafa Abdallah Obeid"
},
"job_title": {
  "ar": "محاسب ومراجع خارجي وخبير دراسات اكتوارية",
  "en": "Accountant, External Auditor, and Actuarial Studies Expert"
},
"nationality": {
  "ar": "مصري",
    "en": "Egyptian"
},
"field": {
  "ar": "المحاسبة والتدقيق الخارجي والاستشارات الاكتوارية",
  "en": "Accounting, External Auditing, and Actuarial Consultancy"
},
"degree": {
  "ar": "بكالوريوس محاسبة",
  "en": "Bachelor's in Accounting"
},
"experience_years": {
  "ar": "20 عام",
  "en": "20 years"
},
"qualifications": [
  {
    "title": {
      "ar": "ماجستير التمويل الإسلامي المعتمد",
      "en": "Certified Master of Islamic Finance"
    },
    "abbreviation": {
      "ar": "MPA",
      "en": "MOA"
    }
  },
  {
    "title": {
      "ar": "حاصل على شهادة معايير المحاسبة الدولية من الجهة المتعاقد معها البريطاني ",
      "en": "certificate of international accounting standards from the British contracting party"
    },
    "abbreviation": {
      "ar": "CERTI IFRS",
      "en": "CERTI IFRS"
    }
  },
  {
    "title": {
      "ar": "حاصل على زمالة المراقب والمدقق الشرعي من هيئة المحاسبة والمراجعة للبنوك والمؤسسات المالية الاسلامية",
      "en": "Fellow of the Sharia Supervisor and Auditor from the Accounting and Auditing Organization for Islamic Banks and Financial Institutions"
    },
    "abbreviation": {
      "ar": "CSAA",
      "en": "CSAA"
    }
  },
  {
    "title": {
      "ar": "بكالوريوس تجارة (تخصص محاسبة)",
      "en": "Bachelor of Commerce (Accounting)"
    }
  }
  ,

  {
    "title": {
      "ar": "العديد من الدورات التدريبية داخل وخارج المملكة العربية السعودية.",
      "en": "Attended numerous training courses inside and outside Saudi Arabia."
    }
  }
],

"image": {
  "url": "https://media.licdn.com/dms/image/v2/D4D0BAQHhTiXcUzqYeA/company-logo_200_200/company-logo_200_200/0/1711368279830/albatel_cpa_logo?e=2147483647&v=beta&t=CgruAhN_mJz9RYhR9nWO3bZJ0NEwfEQ_vQVbocOjEf4",
  "description": {
    "ar": "صورة للسيرة الذاتية لمصطفى عبدالله عبيد",
    "en": "Resume image of Mostafa Abdallah Obeid"
  }
}
},
{
  "id": "6",
  "name": {
    "ar": "رحاب العتيبي",
    "en": "Ruhab Al-Otaibi"
  },
  "job_title": {
    "ar": "محاسب قانوني معتمد",
    "en": "Certified Legal Accountant"
  },
  "nationality": {
    "ar": "سعودية",
    "en": "Saudi"
  },
  "field": {
    "ar": "المحاسبة والمراجعة الداخلية والتدقيق الخارجي",
    "en": "Accounting, Internal Audit, and External Audit"
  },
  "degree": {
    "ar": "بكالوريوس محاسبة",
    "en": "Bachelor's in Accounting"
  },
  "experience_years": {
    "ar": "أكثر من 5 سنوات",
    "en": "More than 5 years"
  },
  "qualifications": [
    {
      "title": {
        "ar": "حاصل على زمالة الهيئة السعودية للمحاسبين القانونيين",
        "en": "Holder of Fellowship from the Saudi Organization for Certified Public Accountants (SOCPA)"
      },
      "abbreviation": {
        "ar": "SOCPA",
        "en": "SOCPA"
      }
    },
    {
      "title": {
        "ar": "اختصاصي ضريبة قيمة مضافة",
        "en": "VAT Specialist"
      },
      "abbreviation": {
        "ar": "VAT",
        "en": "VAT"
      }
    },
    {
      "title": {
        "ar": "العديد من الدورات التدريبية في الضرائب والزكاة وتسعير المعاملات",
        "en": "Completed numerous training courses in VAT, Zakat, and Transaction Pricing"
      }
    },
    {
      "title": {
        "ar": "شهادة البكالوريوس في المحاسبة من جامعة الأميرة نورة بنت عبد الرحمن",
        "en": "Bachelor's degree in Accounting from Princess Nourah bint Abdulrahman University"
      }
    },
    {
      "title": {
        "ar": "العديد من الدورات التدريبية داخل وخارج المملكة العربية السعودية",
        "en": "Attended numerous training courses inside and outside Saudi Arabia"
      }
    }
  ],
  "image": {
    "url": "https://media.licdn.com/dms/image/v2/D4D03AQH3KwDCNfzoKQ/profile-displayphoto-shrink_800_800/profile-displayphoto-shrink_800_800/0/1666789852842?e=1732147200&v=beta&t=f4clxXLHs1Kv_KtSAyVJBSd_XXnrPOFzJQEw1WjZY3s",
    "description": {
      "ar": "صورة للسيرة الذاتية لرحاب العتيبي",
      "en": "Resume image of Ruhab Al-Otaibi"
    }
  }
},
{
  "id": "7",
  "name": {
    "ar": "رزان تركي الحربي",
    "en": "Razan Turki Al-Harbi"
  },
  "job_title": {
    "ar": "محاسب قانوني معتمد",
    "en": "Certified Legal Accountant"
  },
  "nationality": {
    "ar": "سعودية",
    "en": "Saudi"
  },
  "field": {
    "ar": "المحاسبة والمراجعة الداخلية والتدقيق الخارجي",
    "en": "Accounting, Internal Audit, and External Audit"
  },
  "degree": {
    "ar": "بكالوريوس محاسبة",
    "en": "Bachelor's in Accounting"
  },
  "experience_years": {
    "ar": "أكثر من 5 سنوات",
    "en": "More than 5 years"
  },
  "qualifications": [
    {
      "title": {
        "ar": "زمالة المحاسبين القانونيين السعودية",
        "en": "Fellowship of Saudi Certified Accountants"
      },
      "abbreviation": {
        "ar": "SOCPA",
        "en": "SOCPA"
      }
    },
    {
      "title": {
        "ar": "اختصاصي ضريبة قيمة مضافة",
        "en": "VAT Specialist"
      },
      "abbreviation": {
        "ar": "VAT",
        "en": "VAT"
      }
    },
    {
      "title": {
        "ar": "دبلوم المحاسب المحترف في القطاع غير الربحي - الجمعية السعودية للحكومة - جامعة الملك خالد",
        "en": "Professional Accountant Diploma in the Non-Profit Sector - Saudi Governance Association - King Khalid University"
      }
    },
    {
      "title": {
        "ar": "زمالة المستشار الشرعي في فقه المالية الإسلامية وتسوية المنازعات - الجمعية العلمية القضائية الإسلامية - جامعة الإمام محمد بن سعود الإسلامية",
        "en": "Fellow of the Sharia Consultant in Islamic Finance Jurisprudence and Dispute Resolution - Islamic Judiciary Scientific Association - Imam Muhammad bin Saud University"
      }
    },
    {
      "title": {
        "ar": "شهادة البكالوريوس في المحاسبة من جامعة الإمام محمد بن سعود الإسلامية",
        "en": "Bachelor's Degree in Accounting from Imam Muhammad bin Saud Islamic University"
      }
    }
  ],
  "image": {
    "url": "https://media.licdn.com/dms/image/v2/D4D03AQHhS1bxyOHgpQ/profile-displayphoto-shrink_800_800/profile-displayphoto-shrink_800_800/0/1718227955699?e=1732147200&v=beta&t=9PX_PmlnHTV1Vz7ei0DkFIG1AZfj7iR8FKgw1CnImLM",
    "description": {
      "ar": "صورة للسيرة الذاتية لرزان تركي الحربي",
      "en": "Resume image of Razan Turki Al-Harbi"
    }
  }
},
{
  "id": "8",
  "name": {
    "ar": "منيرة الحربي",
    "en": "Muneera Al-Harbi"
  },
  "job_title": {
    "ar": "محاسب قانوني معتمد",
    "en": "Certified Legal Accountant"
  },
  "nationality": {
    "ar": "سعودية",
    "en": "Saudi"
  },
  "field": {
    "ar": "محاسبة ومراجعة داخلية وخارجية",
    "en": "Internal and External Accounting and Auditing"
  },
  "degree": {
    "ar": "بكالوريوس تجارة",
    "en": "Bachelor's in Commerce"
  },
  "experience_years": {
    "ar": "1 سنة",
    "en": "1 year"
  },
  "qualifications": [
    {
      "title": {
        "ar": "بكالوريوس محاسبة",
        "en": "Bachelor's in Accounting"
      }
    },
    {
      "title": {
        "ar": "زمالة الهيئة السعودية للمراجعين والمحاسبين",
        "en": "Fellowship of the Saudi Organization for Certified Public Accountants"
      },
      "abbreviation": {
        "ar": "SOCPA",
        "en": "SOCPA"
      }
    },
    {
      "title": {
        "ar": "عضو أساسي ممارس من الهيئة السعودية للمراجعين",
        "en": "Basic Practicing Member of the Saudi Organization for Auditors"
      },
      "abbreviation": {
        "ar": "SOCPA",
        "en": "SOCPA"
      }
    },
    {
      "title": {
        "ar": "دورة في مستقبل الممارسات البيئية والاجتماعية وحوكمة الشركات",
        "en": "Course in the Future of Environmental, Social, and Corporate Governance Practices"
      }
    },
    {
      "title": {
        "ar": "دورة في الموازنات التقديرية",
        "en": "Course in Budgeting"
      }
    },
    {
      "title": {
        "ar": "دورة المحاسبة القضائية والاحتيال المالي",
        "en": "Course in Forensic Accounting and Financial Fraud"
      }
    },
    {
      "title": {
        "ar": "دورة إدارة المخاطر المالية",
        "en": "Course in Financial Risk Management"
      }
    }
  ],
  "image": {
    "url": "https://www.albatelcpa.com/wp-content/uploads/2023/09/albatel_cpa_logo.jpg",
    "description": {
      "ar": "صورة للسيرة الذاتية لمنيرة الحربي",
      "en": "Resume image of Muneera Al-Harbi"
    }
  }
},
{
  "id": "9",
  "name": {
    "ar": "حور المبارك",
    "en": "Hoor Al-Mubarak"
  },
  "job_title": {
    "ar": "مراجع",
    "en": "Auditor"
  },
  "nationality": {
    "ar": "سعودية",
    "en": "Saudi"
  },
  "field": {
    "ar": "محاسبة",
    "en": "Accounting"
  },
  "degree": {
    "ar": "بكالوريوس محاسبة",
    "en": "Bachelor's in Accounting"
  },
  "experience_years": {
    "ar": "3 سنوات",
    "en": "3 years"
  },
  "qualifications": [
    {
      "title": {
        "ar": "الزمالة السعودية للمحاسبين والمراجعين في الدورة الثالثة",
        "en": "Saudi Fellowship for Accountants and Auditors (Third Cohort)"
      },
      "abbreviation": {
        "ar": "SOCPA",
        "en": "SOCPA"
      }
    },
    {
      "title": {
        "ar": "بكالوريوس في المحاسبة",
        "en": "Bachelor's in Accounting"
      }
    },
    {
      "title": {
        "ar": "تحليل الأعمال من Udacity",
        "en": "Business Analysis from Udacity"
      }
    },
    {
      "title": {
        "ar": "مدير منتج من Udacity",
        "en": "Product Manager from Udacity"
      }
    },
    {
      "title": {
        "ar": "أساسيات إدارة المشاريع المحترفة من مركز نهج القادة",
        "en": "Fundamentals of Professional Project Management from Leadership Path Center"
      }
    },
    {
      "title": {
        "ar": "قراءة القوائم المالية من معهد تمويل الشركات",
        "en": "Reading Financial Statements from the Institute of Corporate Finance"
      }
    },
    {
      "title": {
        "ar": "مقدمة في تمويل الشركات من معهد تمويل الشركات",
        "en": "Introduction to Corporate Finance from the Institute of Corporate Finance"
      }
    },
    {
      "title": {
        "ar": "قراءة القوائم المالية من مركز أصول المهنة",
        "en": "Reading Financial Statements from the Professional Assets Center"
      }
    }
  ],
  "image": {
    "url": "https://www.albatelcpa.com/wp-content/uploads/2023/09/albatel_cpa_logo.jpg",
    "description": {
      "ar": "صورة للسيرة الذاتية لحور المبارك",
      "en": "Resume image of Hoor Al-Mubarak"
    }
  }
},
{
  "id": "10",
  "name": {
    "ar": "فيَ صالح المطيري",
    "en": "Fai Saleh Al-Mutairi"
  },
  "job_title": {
    "ar": "محاسب قانوني",
    "en": "Certified Accountant"
  },
  "nationality": {
    "ar": "سعودية",
    "en": "Saudi"
  },
  "field": {
    "ar": "محاسبة ومراجعة داخلية وخارجية",
    "en": "Accounting and Internal/External Auditing"
  },
  "degree": {
    "ar": "بكالوريوس محاسبة",
    "en": "Bachelor's in Accounting"
  },
  "experience_years": {
    "ar": "4 سنوات و 5 أشهر",
    "en": "4 years and 5 months"
  },
  "qualifications": [
    {
      "title": {
        "ar": "الزمالة السعودية للمحاسبين القانونيين",
        "en": "Saudi Fellowship for Certified Accountants"
      },
      "abbreviation": {
        "ar": "SOCPA",
        "en": "SOCPA"
      }
    }
  ],
  "experience": [
    {
      "role": {
        "ar": "محاسبة مالية",
        "en": "Financial Accounting"
      },
      "period": {
        "ar": "منذ فبراير 2019م حتى فبراير 2020م",
        "en": "From February 2019 to February 2020"
      }
    },
    {
      "role": {
        "ar": "محاسبة عامة",
        "en": "General Accounting"
      },
      "period": {
        "ar": "منذ اغسطس 2020م حتى ديسمبر 2021م",
        "en": "From August 2020 to December 2021"
      }
    },
    {
      "role": {
        "ar": "مشرفة حسابات",
        "en": "Accounts Supervisor"
      },
      "period": {
        "ar": "منذ يناير 2022م حتى يوليو 2023م",
        "en": "From January 2022 to July 2023"
      }
    }
  ],
  "organizations": [
    {
      "name": {
        "ar": "مغسلة كلاود ستيم",
        "en": "Cloud Steam Laundry"
      }
    },
    {
      "name": {
        "ar": "مصنع المتطورون لمنتجات الألمنيوم والزجاج",
        "en": "Advanced Aluminum and Glass Products Factory"
      }
    }
  ],
  "image": {
    "url": "https://media.licdn.com/dms/image/v2/C4E03AQEz79hMYmGMwQ/profile-displayphoto-shrink_800_800/profile-displayphoto-shrink_800_800/0/1613028902770?e=1732147200&v=beta&t=SiWhD6J0-X9O9Pnb_j913uimgro_8p7DzALCop_KpZ0",
    "description": {
      "ar": "صورة للسيرة الذاتية لفي صالح المطيري",
      "en": "Resume image of Saleh Al-Mutairi"
    }
  }
},
{
  "id": "11",
  "name": {
    "ar": "عبد العزيز صالح الحمادي",
    "en": "Abdulaziz Saleh Al-Hammadi"
  },
  "job_title": {
    "ar": "مراجع حسابات",
    "en": "Auditor"
  },
  "nationality": {
    "ar": "سعودي",
    "en": "Saudi"
  },
  "field": {
    "ar": "محاسبة",
    "en": "Accounting"
  },
  "degree": {
    "ar": "بكالوريوس محاسبة",
    "en": "Bachelor's in Accounting"
  },
  "experience_years": {
    "ar": "3 سنوات",
    "en": "3 years"
  },
  "qualifications": [
    {
      "title": {
        "ar": "أخصائي ضريبة القيمة المضافة",
        "en": "VAT Specialist"
      },
      "abbreviation": {
        "ar": "VAT",
        "en": "VAT"
      }
    },
    {
      "title": {
        "ar": "خبرة في تسيير أعمال في مجال المقاولات لمدة 3 سنوات",
        "en": "Experience in Business Management in the Construction Sector for 3 years"
      }
    },
    {
      "title": {
        "ar": "دورة استخدام الحاسب الآلي",
        "en": "Computer Usage Course"
      },
      "institute": {
        "ar": "معهد الخليج للتدريب والتعليم",
        "en": "Gulf Institute for Training and Education"
      }
    },
    {
      "title": {
        "ar": "شهادة اجتياز حتى المستوى الثالث في اللغة الإنجليزية",
        "en": "Passed Level 3 in English Language"
      },
      "institute": {
        "ar": "أكاديمية الفاصل العالمية",
        "en": "Al-Fasil International Academy"
      }
    },
    {
      "title": {
        "ar": "العديد من الدورات المهنية الأخرى داخل المملكة",
        "en": "Various other professional courses within the Kingdom"
      }
    }
  ],
 
  "image": {
    "url": "https://www.albatelcpa.com/wp-content/uploads/2023/09/albatel_cpa_logo.jpg",
    "description": {
      "ar": "صورة للسيرة الذاتية لعبد العزيز صالح الحمادي",
      "en": "Resume image of Abdulaziz Saleh Al-Hammadi"
    }
  }
},
{
  "id": "12",
  "name": {
    "ar": "ريان العضيب",
    "en": "Rayan Al-Odhaib"
  },
  "job_title": {
    "ar": "محاسب ومراجع مالي",
    "en": "Accountant and Financial Auditor"
  },
  "nationality": {
    "ar": "سعودي",
    "en": "Saudi"
  },
  "field": {
    "ar": "محاسبة",
    "en": "Accounting"
  },
  "degree": {
    "ar": "بكالوريوس محاسبة",
    "en": "Bachelor's in Accounting"
  },
  "experience_years": {
    "ar": "3 سنوات و 5 أشهر",
    "en": "3 years and 5 months"
  },
  "qualifications": [
    {
      "title": {
        "ar": "برنامج التدريب على ضريبة القيمة المضافة",
        "en": "VAT Training Program"
      }
    },
    {
      "title": {
        "ar": "برنامج التدريب على نظام الرقابة الداخلية",
        "en": "Training Program on Internal Control System"
      }
    },
    {
      "title": {
        "ar": "برنامج تدريب على أصول المحاسبة الحكومية",
        "en": "Training Program on Fundamentals of Government Accounting"
      }
    },
    {
      "title": {
        "ar": "دورة في البنوك السعودية والمسؤولية الاجتماعية في ظل رؤية 2030",
        "en": "Course on Saudi Banks and Social Responsibility in Light of Vision 2030"
      }
    }
  ],
  "experience": [],
  "organizations": [],
  "image": {
    "url": "https://www.albatelcpa.com/wp-content/uploads/2023/09/albatel_cpa_logo.jpg",
    "description": {
      "ar": "صورة للسيرة الذاتية لريان العضيب",
      "en": "Resume image of Rayan Al-Odhaib"
    }
  }
},
{
  "id": "13",
  "name": {
    "ar": "فيصل الباتل",
    "en": "Faisal Al-Batel"
  },
  "job_title": {
    "ar": "محاسب ومراجع مالي",
    "en": "Accountant and Financial Auditor"
  },
  "nationality": {
    "ar": "سعودي",
    "en": "Saudi"
  },
  "field": {
    "ar": "محاسبة",
    "en": "Accounting"
  },
  "degree": {
    "ar": "بكالوريوس محاسبة",
    "en": "Bachelor's in Accounting"
  },
  "degree_year": {
    "ar": "2019 م",
    "en": "2019"
  },
  "experience_years": {
    "ar": "5 سنوات",
    "en": "5 years"
  },
  "qualifications": [
    {
      "title": {
        "ar": "أخصائي ضريبة القيمة المضافة",
        "en": "VAT Specialist"
      },
      "organization": "VAT"
    },
    {
      "title": {
        "ar": "فني محاسبة",
        "en": "Accounting Technician"
      },
      "organization": "CAT"
    },
    {
      "title": {
        "ar": "العديد من الدورات المهنية الأخرى داخل المملكة",
        "en": "Various other professional courses within the Kingdom"
      }
    }
  ],

  "image": {
    "url": "https://media.licdn.com/dms/image/v2/D4D03AQFkYn7YxlBiyw/profile-displayphoto-shrink_800_800/profile-displayphoto-shrink_800_800/0/1714747665316?e=1732147200&v=beta&t=sOSv8NhNep2lSx3joxGmnzPr4-5TqYU33oumuIXhNPM",
    "description": {
      "ar": "صورة للسيرة الذاتية لفيصل الباتل",
      "en": "Resume image of Faisal Al-Batel"
    }
  }
},
{
  "id": "14",
  "name": {
    "ar": "عبده رمضان أبو عامر",
    "en": "Abduh Ramadan Abu Amer"
  },
  "job_title": {
    "ar": "محاسب ومراجع مالي",
    "en": "Accountant and Financial Auditor"
  },
  "nationality": {
    "ar": "مصري",
    "en": "Egyptian"
  },
  "field": {
    "ar": "محاسبة ومراجعة داخلية وخارجية",
    "en": "Accounting and Internal/External Auditing"
  },
  "degree": {
    "ar": "بكالوريوس محاسبة",
    "en": "Bachelor's in Accounting"
  },
 
  "experience_years": {
    "ar": "13 عام",
    "en": "13 years"
  },
  "qualifications": [
    {
      "title": {
        "ar": "شهادة عضو منتسب للهيئة السعودية للمراجعين والمحاسبين",
        "en": "Affiliate Member Certificate from Saudi Organization for Certified Public Accountants (SOCPA)"
      }
    },
    {
      "title": {
        "ar": "شهادة مكافحة الأموال وتمويل الإرهاب",
        "en": "Anti-Money Laundering and Counter-Terrorism Financing Certificate"
      }
    },
    {
      "title": {
        "ar": "شهادة المعلومات والبينات السنوية التي يتطلبها برنامج مراقبة جودة الأداء المهني",
        "en": "Annual Information and Data Requirement Certificate for Professional Quality Control Program"
      }
    },
    {
      "title": {
        "ar": "برنامج نظام الإفلاس (رؤية محاسبية)",
        "en": "Bankruptcy System Program (Accounting Perspective)"
      }
    },
    {
      "title": {
        "ar": "برنامج ضريبة القيمة المضافة",
        "en": "VAT Program"
      }
    },
    {
      "title": {
        "ar": "خبرة 13 عام في المحاسبة والمراجعة الداخلية والخارجية",
        "en": "13 years of experience in Accounting and Internal/External Auditing"
      }
    },
    {
      "title": {
        "ar": "Accountants' Preparation Course",
        "en": "Accountants' Preparation Course"
      }
    },
    {
      "title": {
        "ar": "برنامج إديو إيجيبت",
        "en": "Edu Egypt Program"
      }
    },
    {
      "title": {
        "ar": "العديد من الدورات التدريبية داخل وخارج المملكة العربية السعودية",
        "en": "Various training courses inside and outside Saudi Arabia"
      }
    }
  ],
  "experience": [],
  "organizations": [],
  "image": {
    "url": "https://www.albatelcpa.com/wp-content/uploads/2023/09/albatel_cpa_logo.jpg",
    "description": {
      "ar": "صورة للسيرة الذاتية لعبده رمضان أبو عامر",
      "en": "Resume image of Abduh Ramadan Abu Amer"
    }
  }
},
{
  "id": "15",
  "name": {
    "ar": "محمد الباتل",
    "en": "Mohammed Al-Batel"
  },
  "job_title": {
    "ar": "محاسب ومراجع مالي",
    "en": "Accountant and Financial Auditor"
  },
  "nationality": {
    "ar": "سعودي",
    "en": "Saudi"
  },
  "field": {
    "ar": "محاسبة",
    "en": "Accounting"
  },
  "degree": {
    "ar": "بكالوريوس محاسبة",
    "en": "Bachelor's in Accounting"
  },
  "degree_year": {
    "ar": "2017 م",
    "en": "2017"
  },
  "experience_years": {
    "ar": "6 سنوات و6 أشهر",
    "en": "6 years and 6 months"
  },
  "qualifications": [
    {
      "title": {
        "ar": "المعيار الدولي للتقرير المالي للمنشآت الصغيرة والمتوسطة - الجزء الأول والثاني والثالث",
        "en": "IFRS for SMEs - Parts I, II, and III"
      }
    },
    {
      "title": {
        "ar": "اخصائي ضريبة القيمة المضافة",
        "en": "VAT Specialist"
      }
    },
    {
      "title": {
        "ar": "مبادئ تقييم العقاري الاساسية",
        "en": "Principles of Basic Real Estate Valuation"
      }
    },
    {
      "title": {
        "ar": "اجراءات تقييم العقاري الاساسية",
        "en": "Procedures of Basic Real Estate Valuation"
      }
    },
    {
      "title": {
        "ar": "مقدمة الى المعايير التقييم الدولية ونظام ولائحة المقيمين المعتمدين وميثاق آداب وسلوك مهنة التقييم",
        "en": "Introduction to International Valuation Standards, Certified Evaluators’ Regulations, and Code of Conduct for the Valuation Profession"
      }
    },
    {
      "title": {
        "ar": "التقييم العقاري باستخدام اسلوب التكلفة وايضاً في التسوق والدخل",
        "en": "Real Estate Valuation Using Cost Approach, as well as Market and Income Approaches"
      }
    },
    {
      "title": {
        "ar": "اوراق عمل مراجعة",
        "en": "Review Working Papers"
      }
    },
    {
      "title": {
        "ar": "نظام الإفلاس رؤية محاسبية",
        "en": "Bankruptcy Law from an Accounting Perspective"
      }
    },
    {
      "title": {
        "ar": "والعديد من الدورات الأخرى داخل المملكة",
        "en": "Various other courses within Saudi Arabia"
      }
    }
  ],
  
  "image": {
    "url": "https://www.albatelcpa.com/wp-content/uploads/2023/09/albatel_cpa_logo.jpg",
    "description": {
      "ar": "صورة للسيرة الذاتية لمحمد الباتل",
      "en": "Resume image of Mohammed Al-Batel"
    }
  }
},
{
  "id": "16",
  "name": {
    "ar": "محمد الدبلان",
    "en": "Mohammed Al-Dablan"
  },
  "job_title": {
    "ar": "محاسب ومراجع مالي",
    "en": "Accountant and Financial Auditor"
  },
  "nationality": {
    "ar": "سعودي",
    "en": "Saudi"
  },
  "field": {
    "ar": "محاسبة",
    "en": "Accounting"
  },
  "degree": {
    "ar": "بكالوريوس في المحاسبة",
    "en": "Bachelor's in Accounting"
  },
  "experience_years": {
    "ar": "3 سنوات",
    "en": "3 years"
  },
  "qualifications": [
    {
      "title": {
        "ar": "شهادة الزكاة والضريبة",
        "en": "VAT and Zakat Certification"
      },
      "abbreviation": {
        "ar": "VAT-Zakat-Tax",
        "en": "VAT-Zakat-Tax"
      }
    }
  ],
  "image": {
    "url": "https://media.licdn.com/dms/image/v2/C4D03AQHQU5CX5v3k8Q/profile-displayphoto-shrink_800_800/profile-displayphoto-shrink_800_800/0/1662416238867?e=1732147200&v=beta&t=JuvGSyYPALbpJzIBQPkb8zzSt_i7XLye6Pi9qfGHSoE",
    "description": {
      "ar": "صورة للسيرة الذاتية لمحمد الدبلان",
      "en": "Resume image of Mohammed Al-Dablan"
    }
  }
},
{
  "id": "17",
  "name": {
    "ar": "عبدالإله الطريقي",
    "en": "Abdullah Al-Turaiki"
  },
  "job_title": {
    "ar": "محاسب ومراجع مالي",
    "en": "Accountant and Financial Auditor"
  },
  "nationality": {
    "ar": "سعودي",
    "en": "Saudi"
  },
  "field": {
    "ar": "محاسبة",
    "en": "Accounting"
  },
  "degree": {
    "ar": "بكالوريوس في المحاسبة",
    "en": "Bachelor's in Accounting"
  },
  "experience_years": {
    "ar": "4 سنوات و 10 أشهر",
    "en": "4 years and 10 months"
  },
  "year_obtained": {
    "ar": "2022",
    "en": "2022"
  },
  "qualifications": [
    {
      "title": {
        "ar": "بكالوريوس في إدارة الأعمال تخصص محاسبة",
        "en": "Bachelor's in Business Administration with a specialization in Accounting"
      }
    },
    {
      "title": {
        "ar": "شهادة من معرض الأولمبياد الوطني للإبداع العلمي",
        "en": "Certificate from the National Olympiad for Scientific Creativity"
      }
    },
    {
      "title": {
        "ar": "شهادة برنامج تدريبي بعنوان 'الفساد الالكتروني'",
        "en": "Certification from a training program titled 'Electronic Fraud'"
      }
    }
  ],
  "image": {
    "url": "https://media.licdn.com/dms/image/v2/D4E03AQFWwmOrJlMGig/profile-displayphoto-shrink_800_800/profile-displayphoto-shrink_800_800/0/1715339847874?e=1732147200&v=beta&t=LnhINNIEaEu1fLi1rGAHKdEnWbeOLGbxVB_RAhq9VKU",
    "description": {
      "ar": "صورة للسيرة الذاتية لعبدالإله الطريقي",
      "en": "Resume image of Abdullah Al-Turaiki"
    }
  }
}
 

  ],
  "team2":[
    {
      "id": "18",
      "name": {
        "ar": "عصام السيد حسن السروجي",
        "en": "Issam El-Sayed Hassan El-Sarogy"
      },
      "job_title": {
        "ar": "مستشار إداري",
        "en": "Management Consultant"
      },
      "nationality": {
        "ar": "مصري",
        "en": "Egyptian"
      },
      "field": {
        "ar": "استشارات إدارية واقتصادية والسياسات والحوكمة",
        "en": "Management, Economic Consulting, Policy, and Governance"
      },
      "degree": {
        "ar": "بكالوريوس تجارة",
        "en": "Bachelor's in Commerce"
      },
      "year_obtained": {
        "ar": "1980م",
        "en": "1980"
      },
      "experience_years": {
        "ar": "تزيد عن 25 عام",
        "en": "Over 25 years"
      },
      "qualifications": [
        {
          "title": {
            "ar": "دبلومة تطوير النظم الإدارية",
            "en": "Diploma in Administrative Systems Development"
          }
        },
        {
          "title": {
            "ar": "دبلومة إعداد الدراسات الاقتصادية",
            "en": "Diploma in Economic Studies Preparation"
          }
        },
        {
          "title": {
            "ar": "العديد من الدورات التدريبية داخل وخارج المملكة العربية السعودية",
            "en": "Numerous training courses inside and outside Saudi Arabia"
          }
        }
      ],
      "image": {
        "url": "https://media.licdn.com/dms/image/v2/D4D0BAQHhTiXcUzqYeA/company-logo_200_200/company-logo_200_200/0/1711368279830/albatel_cpa_logo?e=2147483647&v=beta&t=CgruAhN_mJz9RYhR9nWO3bZJ0NEwfEQ_vQVbocOjEf4",
        "description": {
          "ar": "صورة للسيرة الذاتية لعصام السيد حسن السروجي",
          "en": "Resume image of Issam El-Sayed Hassan El-Sarogy"
        }
      }
    },
    {
      "id": "19",
      "name": {
        "ar": "محمد عبد المجيد",
        "en": "Mohammed Abdel Magid"
      },
      "job_title": {
        "ar": "مستشار مالي وإداري",
        "en": "Financial and Administrative Consultant"
      },
      "nationality": {
        "ar": "مصري",
        "en": "Egyptian"
      },
      "field": {
        "ar": "محاسبة ومراجعة داخلية وتحليل بيانات",
        "en": "Accounting, Internal Auditing, and Data Analysis"
      },
      "degree": {
        "ar": "بكالوريوس محاسبة",
        "en": "Bachelor's in Accounting"
      },
      "year_obtained": {
        "ar": "1996",
        "en": "1996"
      },
      "experience_years": {
        "ar": "تزيد عن 25 عام",
        "en": "Over 25 years"
      },
      "qualifications": [
        {
          "title": {
            "ar": "شهادة الائتمان والتحليل المالي للشركات من برنامج سيتي بنك من الجامعة الأمريكية بالقاهرة",
            "en": "Credit and Financial Analysis for Companies Certification from Citibank Program, American University in Cairo, 2011"
          }
        },
        {
          "title": {
            "ar": "شهادة المقرض المعتمد بالمصارف التجارية المعتمدة من اتحاد المصارف (التحليل المالي واحتياجات التمويل للشركات) من الأكاديمية العربية للعلوم المالية والمصرفية",
            "en": "Certified Commercial Lender Certification from Banking Federation (Financial Analysis and Financing Needs for Companies), Arab Academy for Financial and Banking Sciences, 2005"
          }
        },
        {
          "title": {
            "ar": "شهادة البكالوريوس في المحاسبة من جامعة طنطا 1996",
            "en": "Bachelor's degree in Accounting from Tanta University 1996"
          }
        },
        {
          "title": {
            "ar": "العديد من الدورات التدريبية داخل وخارج المملكة العربية السعودية",
            "en": "Numerous training courses inside and outside Saudi Arabia"
          }
        }
      ],
      "image": {
        "url": "https://media.licdn.com/dms/image/v2/D4D0BAQHhTiXcUzqYeA/company-logo_200_200/company-logo_200_200/0/1711368279830/albatel_cpa_logo?e=2147483647&v=beta&t=CgruAhN_mJz9RYhR9nWO3bZJ0NEwfEQ_vQVbocOjEf4",
        "description": {
          "ar": "صورة للسيرة الذاتية لمحمد عبد المجيد",
          "en": "Resume image of Mohammed Abdel Magid"
        }
      }
    },
    {
      "id": "20",
      "name": {
        "ar": "محمد عجور",
        "en": "Mohammed Ajour"
      },
      "job_title": {
        "ar": "مستشار إداري",
        "en": "Management Consultant"
      },
      "nationality": {
        "ar": "مصر",
        "en": "Egyptian"
      },
      "field": {
        "ar": " الاستشارات الإدارية وإدارة المشروعات و الترجمة",
        "en": "Management Consulting and Project Management and translation"
      },
      "degree": {
        "ar": "ماجستير إدارة الأعمال",
        "en": "Master's in Business Administration (MBA)"
      },
      "year_obtained": {
        "ar": "2021",
        "en": "2021"
      },
      "experience_years": {
        "ar": "10 سنوات",
        "en": "10 years"
      },
      "qualifications": [
        {
          "title": {
            "ar": "ماجستير إدارة الأعمال تخصص: PGD-Global Management",
            "en": "Master's in Business Administration, Specialization: PGD-Global Management"
          }
        },
        {
          "title": {
            "ar": "شهادة إدارة المشاريع المحترفة (PMP) من الجامعة الأمريكية بالقاهرة (AUC) عام 2018",
            "en": "Project Management Professional (PMP) Certification from the American University in Cairo (AUC), 2018"
          }
        },
        {
          "title": {
            "ar": "شهادة أخصائي إدارة مخاطر (RMP)",
            "en": "Risk Management Professional (RMP) Certification"
          }
        },
        {
          "title": {
            "ar": "شهادة حوكمة الشركات (PCCG)",
            "en": "Professional Certificate in Corporate Governance (PCCG)"
          }
        },
        {
          "title": {
            "ar": "ليسانس اللغات والترجمة شعبة: الترجمة الفورية بالإنجليزية من جامعة الأزهر بتقدير جيد جداً مع مرتبة الشرف",
            "en": "Bachelor's in Languages and Translation, Specialization: Simultaneous Interpretation in English, Al-Azhar University, with Very Good Honors"
          }
        },
        {
          "title": {
            "ar": "دورة مراقبة الأداء والتقييم الفعالة",
            "en": "Effective Performance Monitoring and Evaluation Course"
          }
        },
        {
          "title": {
            "ar": "دورة ترجمة وتفسير العلوم الاجتماعية من المركز القومي للترجمة",
            "en": "Translation and Interpretation of Social Sciences Course from the National Center for Translation"
          }
        },
        {
          "title": {
            "ar": "دورة تنمية بشرية بعنوان 'Job Hunting'",
            "en": "Human Development Course titled 'Job Hunting'"
          }
        },
        {
          "title": {
            "ar": "والعديد من الدورات التدريبية خارج المملكة العربية السعودية",
            "en": "Numerous training courses outside Saudi Arabia"
          }
        }
      ],
      "image": {
        "url": "https://media.licdn.com/dms/image/v2/C4D03AQFpmrmnb3vBRw/profile-displayphoto-shrink_800_800/profile-displayphoto-shrink_800_800/0/1591048603188?e=1732147200&v=beta&t=j5sYkL8g0iJr8anv6TYX5YkfjIQGng_adGpx6_LWMS4",
        "description": {
          "ar": "صورة للسيرة الذاتية لمحمد عجور",
          "en": "Resume image of Mohammed Ajour"
        }
      }
    },
    {
      "id": "21",
      "name": {
        "ar": "عمر النصار",
        "en": "Omar Al-Nassar"
      },
      "job_title": {
        "ar": "مترجم",
        "en": "Translator"
      },
      "nationality": {
        "ar": "سعودي",
        "en": "Saudi"
      },
      "field": {
        "ar": "الترجمة",
        "en": "Translation"
      },
      "degree": {
        "ar": "بكالوريوس انجليزي",
        "en": "Bachelor's in English"
      },
      
      "experience_years": {
        "ar": "1 سنة و9 أشهر",
        "en": "1 year and 9 months"
      },
      "qualifications": [
        {
          "title": {
            "ar": "بكالوريوس في اللغة الإنجليزية",
            "en": "Bachelor's in English"
          }
        }
      ],
      "image": {
        "url": "https://pbs.twimg.com/profile_images/1772264055920603136/nHhDFMe2_400x400.jpg",
        "description": {
          "ar": "صورة للسيرة الذاتية لعمر النصار",
          "en": "Resume image of Omar Al-Nassar"
        }
      }
    } 
  ],
  "team3":[
    {
      "id": "22",
      "name": {
        "ar": "مصطفى مدحت",
        "en": "Mostafa Medhat"
      },
      "job_title": {
        "ar": "خبير ومدقق ضريبي",
        "en": "Tax Expert and Auditor"
      },
      "nationality": {
        "ar": "مصري",
        "en": "Egyptian"
      },
      "field": {
        "ar": "المحاسبة الضريبية وضريبة القيمة المضافة",
        "en": "Tax Accounting and VAT"
      },
      "degree": {
        "ar": "بكالوريوس محاسبة",
        "en": "Bachelor's in Accounting"
      },
      "year_obtained": {
        "ar": "2002",
        "en": "2002"
      },
      "experience_years": {
        "ar": "تزيد عن 21 عام",
        "en": "Over 21 years"
      },
      "qualifications": [
        {
          "title": {
            "ar": "حاصل على أكثر من 20 برنامج تدريبي بمراكز التدريب بمصلحة الضرائب المصرية في موضوعات منها: فحص النظم الآلية، فحص قضايا التهرب الضريبي، فحص الحسابات الغير منتظمة، إجراءات الخصم الضريبي، إجراءات رد الضريبة، وغيرها من المجالات الضريبية.",
            "en": "Completed over 20 training programs at the Egyptian Tax Authority Training Centers on topics such as: System Audits, Tax Evasion Cases, Irregular Accounts Audits, Tax Deduction Procedures, Tax Refund Procedures, and other tax-related fields."
          }
        },
        {
          "title": {
            "ar": "حاصل على بكالوريوس تجارة شعبة محاسبة",
            "en": "Bachelor's in Commerce with a specialization in Accounting"
          }
        },
        {
          "title": {
            "ar": "مأمور فحص بمصلحة الضرائب المصرية قيمة مضافة لمدة تزيد على 21 عام منها 4 سنوات رئيس مجموعة فحص",
            "en": "Tax Auditor at the Egyptian Tax Authority for over 21 years, including 4 years as Head of the Audit Group"
          }
        },
        {
          "title": {
            "ar": "العديد من الدورات التدريبية فى المجالات المحاسبية والمالية خارج المملكة العربية السعودية",
            "en": "Numerous training courses in accounting and financial fields outside Saudi Arabia"
          }
        }
      ],
      "image": {
        "url": "https://pbs.twimg.com/profile_images/1772264055920603136/nHhDFMe2_400x400.jpg",
        "description": {
          "ar": "صورة للسيرة الذاتية لمصطفى مدحت",
          "en": "Resume image of Mostafa Medhat"
        }
      }
    }
    
  ],
  "team4":[
    {
      "id": "23",
      "name": {
        "ar": "محمد فرحات",
        "en": "Mohammed Farhat"
      },
      "job_title": {
        "ar": "مستشار قانوني",
        "en": "Legal Consultant"
      },
      "nationality": {
        "ar": "مصري",
        "en": "Egyptian"
      },
      "field": {
        "ar": "الاستشارات القانونية",
        "en": "Legal Consulting"
      },
      "degree": {
        "ar": "ماجستير في القانون",
        "en": "Master's in Law"
      },
  
      "experience_years": {
        "ar": "أكثر من 7 سنوات",
        "en": "Over 7 years"
      },
      "qualifications": [
        {
          "title": {
            "ar": "دبلومة في صياغة العقود من جامعة هارفرد",
            "en": "Diploma in Contract Drafting from Harvard University"
          }
        },
        {
          "title": {
            "ar": "محكم دولي معتمد وعضو المعهد القانوني للوسطاء والمحكمين المملكة المتحدة بلندن",
            "en": "Certified International Arbitrator and Member of the Chartered Institute of Arbitrators in London, UK"
          }
        },
        {
          "title": {
            "ar": "عضوية الجمعية القانونية بإنجلترا",
            "en": "Member of the Law Society of England"
          }
        },
        {
          "title": {
            "ar": "عضو المنظمة العالمية للملكية الفكرية",
            "en": "Member of the World Intellectual Property Organization (WIPO)"
          }
        },
        {
          "title": {
            "ar": "دبلومة في القانون الإداري من جامعة الإسكندرية",
            "en": "Diploma in Administrative Law from Alexandria University"
          }
        },
        {
          "title": {
            "ar": "دورة إعداد وصياغة وترجمة العقود المدنية باللغتين العربية والانجليزية من كلية الحقوق جامعة الإسكندرية",
            "en": "Course in Drafting, Preparing, and Translating Civil Contracts in Arabic and English from the Faculty of Law, Alexandria University"
          }
        },
        {
          "title": {
            "ar": "دورة مبادئ الموارد البشرية دبي",
            "en": "Human Resources Principles Course, Dubai"
          }
        },
        {
          "title": {
            "ar": "والعديد من الدورات التدريبية داخل وخارج المملكة العربية السعودية",
            "en": "Numerous training courses inside and outside Saudi Arabia"
          }
        }
      ],
      "image": {
        "url": "https://pbs.twimg.com/profile_images/1772264055920603136/nHhDFMe2_400x400.jpg",
        "description": {
          "ar": "صورة للسيرة الذاتية لمحمد فرحات",
          "en": "Resume image of Mohammed Farhat"
        }
      }
    }
    
  ],
  "team5":[
    { "id":"24",
    "name": {
      "ar": "أحمد محمد سعد عبدالدايم",
      "en": "Ahmed Mohamed Saad Abdeldaiem"
    },
    "job_title": {
      "ar": "مبرمج مواقع وتطبيقات ومحلل بيانات",
      "en": "Website and App Developer and Data Analyst"
    },
    "nationality": {
      "ar": "مصري",
      "en": "Egyptian"
    },
    "field": {
      "ar": "  تحليل البيانات وإدارة المشروعات و تطوير المواقع الالكترونية",
      "en": "Data Analysis, Project Management and Website Development"
    },
    "degree": {
      "ar": "بكالريوس حاسبات زمعلومات",
      "en": "Bachelor of Computers and Information"
    },
    "experience_years": {
      "ar": "أكثر من 5 سنة",
      "en": "More than 5 years"
    },
    "qualifications": [
      {
        "title": {
          "ar": "بكالريوس الحاسبات والمعلومات جامعة قناة السويس بتقدير جيدجدا مع مرتبة الشرف لعام 2016",
          "en": "Bachelor of Computer Science and Information, Suez Canal University, with a very good grade with honors, 2016"
        }
      },
      {
        "title": {
          "ar": "خبرة اكثر من ثلاث سنوات من العمل على بيانات شركات الاتصالات وتحليل بيانات العملاء والموظفين",
          "en": "More than three years of experience working on telecom companies' data and analyzing customer and employee data"
        }
      },
      {
        "title": {
          "ar": "دبلومة تطوير الواجهة الأمامية معتمدة من مركز تدريب Route IT",
          "en": "front end development diploma certified by Route IT Training Center"
        }
      }
      
    ],
   
    "image": {
      "url": "blob:https://web.whatsapp.com/47a2f10e-ee15-4121-a84b-6486d24d93de",
      "description": {
        "ar": "صورة للسيرة الذاتية لأحمد محمد سعد عبدالدايم",
        "en": "Resume image of Ahmed Mohamed Abdeldaiem"
      }
    }
  }
  ]
}